tcx2gpx/__init__.py
tcx2gpx/_version.py
tcx2gpx/batch.py
tcx2gpx/tcx2gpx.py
tcx2gpx-0.1.6.dist-info/licenses/COPYING
tcx2gpx-0.1.6.dist-info/METADATA
tcx2gpx-0.1.6.dist-info/WHEEL
tcx2gpx-0.1.6.dist-info/entry_points.txt
tcx2gpx-0.1.6.dist-info/top_level.txt
tcx2gpx-0.1.6.dist-info/RECORD
