Metadata-Version: 2.4
Name: tcx2gpx
Version: 0.1.6
Summary: Convert Garmin TCX GPS tracks to GPX
Author-email: Neil Shephard <nshephard@gmail.com>
License: GNU GPLv3 only
Project-URL: Bug_Tracker, https://codeberg.org/slackline/tcx2gpx/issues/
Project-URL: Source, https://codeberg.org/slackline/tcx2gpx
Project-URL: Documentation, https://tcx2gpx.readthedocs.io/en/latest/
Classifier: License :: OSI Approved :: GNU General Public License v3 (GPLv3)
Classifier: Natural Language :: English
Classifier: Operating System :: OS Independent
Classifier: Programming Language :: Python :: 3
Classifier: Topic :: Text Processing :: Markup :: XML
License-File: COPYING
Requires-Dist: gpxpy
Requires-Dist: python_dateutil
Requires-Dist: python_tcxparser
Requires-Dist: tqdm
Provides-Extra: dev
Requires-Dist: black; extra == "dev"
Requires-Dist: codespell; extra == "dev"
Requires-Dist: ipdb; extra == "dev"
Requires-Dist: pre-commit; extra == "dev"
Requires-Dist: pydocstyle[toml]; extra == "dev"
Requires-Dist: pylint; extra == "dev"
Requires-Dist: pytest-testmon; extra == "dev"
Requires-Dist: ruff; extra == "dev"
Requires-Dist: tomli; extra == "dev"
Provides-Extra: docs
Requires-Dist: mkdocs; extra == "docs"
Requires-Dist: mkdocs-material; extra == "docs"
Requires-Dist: mkdocs-mermaid2-plugin; extra == "docs"
Requires-Dist: mkdocstrings[python]; extra == "docs"
Requires-Dist: numpydoc; extra == "docs"
Provides-Extra: pypi
Requires-Dist: build; extra == "pypi"
Requires-Dist: pytest-runner; extra == "pypi"
Requires-Dist: setuptools-lint; extra == "pypi"
Requires-Dist: setuptools_scm; extra == "pypi"
Requires-Dist: twine; extra == "pypi"
Requires-Dist: wheel; extra == "pypi"
Provides-Extra: test
Requires-Dist: pytest; extra == "test"
Requires-Dist: pytest-cov; extra == "test"
Dynamic: license-file
